{
  "configVersion": 1,
  "timestamp": 1560594325715,
  "index": "/index.html",
  "assetGroups": [
    {
      "name": "app",
      "installMode": "prefetch",
      "updateMode": "prefetch",
      "urls": [
        "/10.108f4f61eb9f10900caa.js",
        "/11.93f27728526c4897a6f1.js",
        "/5.f94e2fd6270eff6a64af.js",
        "/6.76df256ca1a6e8aaaaa6.js",
        "/7.21d7051352fd69ff817e.js",
        "/8.77ce34910425c3acd1c3.js",
        "/9.fad1d13ac49d795adadb.js",
        "/common.8c2d72937b4bf268a3f8.js",
        "/favicon.ico",
        "/index.html",
        "/main.05aa08ee15a6befb2597.js",
        "/polyfills.4c5b9e56bee37e622d5a.js",
        "/runtime.251f7675df4c2dc695a3.js",
        "/styles.b72cb5e5f9d721810348.css"
      ],
      "patterns": []
    },
    {
      "name": "assets",
      "installMode": "lazy",
      "updateMode": "prefetch",
      "urls": [
        "/assets/icons/icon-128x128.png",
        "/assets/icons/icon-144x144.png",
        "/assets/icons/icon-152x152.png",
        "/assets/icons/icon-192x192.png",
        "/assets/icons/icon-384x384.png",
        "/assets/icons/icon-512x512.png",
        "/assets/icons/icon-72x72.png",
        "/assets/icons/icon-96x96.png",
        "/assets/img/perfil.png",
        "/assets/img/uoc_logo.png"
      ],
      "patterns": []
    }
  ],
  "dataGroups": [],
  "hashTable": {
    "/10.108f4f61eb9f10900caa.js": "37f75a594c5abdd275788c1a93e89c6656bbd4df",
    "/11.93f27728526c4897a6f1.js": "c0491afdbdc7164ae1403d919a34f0a3a27e51ea",
    "/5.f94e2fd6270eff6a64af.js": "707c1f7285eb9a387ebdaed29cb97294c5c80b5a",
    "/6.76df256ca1a6e8aaaaa6.js": "2022fff07092c66116e808f1128cb3c4b5be6d69",
    "/7.21d7051352fd69ff817e.js": "8356f0ac392f80932593bf7e1f9090230b9ef0b1",
    "/8.77ce34910425c3acd1c3.js": "bbebe1d333aa1edaceb10565ff24db10e9596906",
    "/9.fad1d13ac49d795adadb.js": "ceded56f2d533258339a3d47fdf00408bbbd8eca",
    "/assets/icons/icon-128x128.png": "dae3b6ed49bdaf4327b92531d4b5b4a5d30c7532",
    "/assets/icons/icon-144x144.png": "b0bd89982e08f9bd2b642928f5391915b74799a7",
    "/assets/icons/icon-152x152.png": "7479a9477815dfd9668d60f8b3b2fba709b91310",
    "/assets/icons/icon-192x192.png": "1abd80d431a237a853ce38147d8c63752f10933b",
    "/assets/icons/icon-384x384.png": "329749cd6393768d3131ed6304c136b1ca05f2fd",
    "/assets/icons/icon-512x512.png": "559d9c4318b45a1f2b10596bbb4c960fe521dbcc",
    "/assets/icons/icon-72x72.png": "c457e56089a36952cd67156f9996bc4ce54a5ed9",
    "/assets/icons/icon-96x96.png": "3914125a4b445bf111c5627875fc190f560daa41",
    "/assets/img/perfil.png": "c34d68aa614df190342bf4ccfb05fabce3561034",
    "/assets/img/uoc_logo.png": "a8268228316a687fc11a0ecbedb2507aedcccf39",
    "/common.8c2d72937b4bf268a3f8.js": "9549178104a35b24baa10dd0872fe592a56b6cfb",
    "/favicon.ico": "84161b857f5c547e3699ddfbffc6d8d737542e01",
    "/index.html": "9be0b32d60354de8986340e2354548a1d04768d9",
    "/main.05aa08ee15a6befb2597.js": "004a3541576a6978247dc0e5d41ddd5d989bf10b",
    "/polyfills.4c5b9e56bee37e622d5a.js": "ad54388e3f78ff96aaa4c3808b17569aa45c16c4",
    "/runtime.251f7675df4c2dc695a3.js": "6f292127944e4d8a0491ca381da87451e2b6a498",
    "/styles.b72cb5e5f9d721810348.css": "eba9ddbd3aca8c0541a8a5f09d21d7a137ab5333"
  },
  "navigationUrls": [
    {
      "positive": true,
      "regex": "^\\/.*$"
    },
    {
      "positive": false,
      "regex": "^\\/(?:.+\\/)?[^/]*\\.[^/]*$"
    },
    {
      "positive": false,
      "regex": "^\\/(?:.+\\/)?[^/]*__[^/]*$"
    },
    {
      "positive": false,
      "regex": "^\\/(?:.+\\/)?[^/]*__[^/]*\\/.*$"
    }
  ]
}